<SheffieldHYS id="17357">
<BaseURL><entry>http://www.sheffieldhelpyourself.org.uk/full_search_new.asp?group=17357</entry>
</BaseURL>
<HYSID><entry>17357</entry>
</HYSID>
<OrgName><entry>NETHERLANDS, THE KINGDOM OF - CONSUL FOR</entry>
</OrgName>
<Desc><entry>The Consul for The Kingdom of The Netherlands provides passports and visas to people visiting the Netherlands.</entry>
</Desc>
<Website><entry>http://www.netherlands-embassy.org.uk</entry>
</Website>
<Langs><entry>Dutch</entry>
</Langs>
<Address><entry>Apex House</entry>
<entry>266 Moseley Road</entry>
<entry>Manchester</entry>
<entry>Cheshire</entry>
<entry>M19 2LH</entry>
</Address>
<DisabledAccess><entry>Wheelchair Accessible;</entry>
<entry>Wheelchair Accessible with Assistance;</entry>
<entry>Wheelchair Accessible Toilet;</entry>
</DisabledAccess>
<ContactName><entry>Mr I B Perry, Consul/Mrs Slater, Consular Officer</entry>
</ContactName>
<Telephone><entry>0161 248 2390</entry>
<entry>Telephone 1 Details:</entry>
<entry>Mon-Fri 10am-3pm</entry>
</Telephone>
<Fax><entry>0161 225 2837</entry>
</Fax>
<Email><entry>mieke.slater@harvesthousing.org.uk</entry>
</Email>
<ProviderServiceDetails><entry>Mon-Fri 10am-3pm (office). Visiting times by arrangement, please contact for an appointment</entry>
</ProviderServiceDetails>
<category><entry>CONSULAR REPRESENTATIVES</entry>
</category>
</SheffieldHYS>
