<SheffieldHYS id="17551">
<BaseURL><entry>http://www.sheffieldhelpyourself.org.uk/full_search_new.asp?group=17551</entry>
</BaseURL>
<HYSID><entry>17551</entry>
</HYSID>
<OrgName><entry>DEERLANDS RESIDENTIAL CARE HOME</entry>
</OrgName>
<Desc><entry>Voluntary sector residential care home run by Sheffcare Ltd, a not-for-profit provider of care.  40 beds.  This care home is registered and inspected by the Care Quality Commission (CQC), to make sure they provide a quality service.</entry>
</Desc>
<Website><entry>http://www.sheffcare.co.uk</entry>
</Website>
<CharityNo><entry>1054227</entry>
</CharityNo>
<Address><entry>48 Margetson Road</entry>
<entry>Sheffield</entry>
<entry>South Yorkshire</entry>
<entry>S5 9LS</entry>
</Address>
<DisabledAccess><entry>Wheelchair Accessible;</entry>
<entry>Wheelchair Accessible Toilet;</entry>
</DisabledAccess>
<ContactName><entry>Diane Iwanejko, Registered Manager</entry>
</ContactName>
<Telephone><entry>0114 221 3258</entry>
</Telephone>
<Fax><entry>0114 221 3259</entry>
</Fax>
<Email><entry>diane.iwanejko@sheffcare.co.uk</entry>
</Email>
<category><entry>CARE HOMES FOR OLDER PEOPLE (RESIDENTIAL HOMES)</entry>
</category>
</SheffieldHYS>
