<SheffieldHYS id="19259">
<BaseURL><entry>http://www.sheffieldhelpyourself.org.uk/full_search_new.asp?group=19259</entry>
</BaseURL>
<HYSID><entry>19259</entry>
</HYSID>
<OrgName><entry>NIAGARA BOWLS CLUB</entry>
</OrgName>
<Desc><entry>Club for female, male and veteran players.</entry>
</Desc>
<Address><entry>Please contact for details</entry>
</Address>
<ContactName><entry>Mr K McSloy</entry>
</ContactName>
<Telephone><entry>0114 234 8112</entry>
</Telephone>
<Provision><ProvisionPlace><entry>Niagara Sports Club</entry>
<entry>Niagara Road</entry>
<entry>Sheffield</entry>
<entry>South Yorkshire</entry>
<entry>S6 1LU</entry>
</ProvisionPlace>
<ProvisionPlaceDisabledAccess><entry>Wheelchair Accessible;</entry>
<entry>Wheelchair Accessible Toilet;</entry>
<entry>Further Access Details:</entry>
<entry>Lift</entry>
</ProvisionPlaceDisabledAccess>
<ProvisionDaysAndTimes><entry>Please contact for details</entry>
<entry>Contact Name:</entry>
<entry>Peter Darling, Chief Executive</entry>
</ProvisionDaysAndTimes>
<Telephone><entry>0114 296 4946</entry>
</Telephone>
</Provision>
<category><entry>BOWLS</entry>
</category>
</SheffieldHYS>
