<SheffieldHYS id="21440">
<BaseURL><entry>http://www.sheffieldhelpyourself.org.uk/full_search_new.asp?group=21440</entry>
</BaseURL>
<HYSID><entry>21440</entry>
</HYSID>
<OrgName><entry>WADSLEY JACK BOWLS CLUB</entry>
</OrgName>
<Desc><entry>Club for female, male and veteran players.</entry>
</Desc>
<Address><entry>Please contact for details</entry>
</Address>
<ContactName><entry>Mrs M Waller</entry>
</ContactName>
<Telephone><entry>0114 233 2404</entry>
</Telephone>
<Provision><ProvisionPlace><entry>Wadsley Jack Inn</entry>
<entry>Rural Lane</entry>
<entry>Sheffield</entry>
<entry>South Yorkshire</entry>
<entry>S6 4BJ</entry>
</ProvisionPlace>
<ProvisionPlaceDisabledAccess><entry>Wheelchair Accessible with Assistance;</entry>
<entry>Wheelchair Accessible Toilet;</entry>
</ProvisionPlaceDisabledAccess>
<Telephone><entry>0114 234 3243</entry>
</Telephone>
</Provision>
<category><entry>BOWLS</entry>
</category>
</SheffieldHYS>
