<SheffieldHYS id="21500">
<BaseURL><entry>http://www.sheffieldhelpyourself.org.uk/full_search_new.asp?group=21500</entry>
</BaseURL>
<HYSID><entry>21500</entry>
</HYSID>
<OrgName><entry>WELLBEING OF WOMEN (WOW)</entry>
</OrgName>
<Desc><entry>Fundraising arm of the Royal College of Obstetricians and Gynaecologists.  Funds medical and scientific research into all aspects of childbirth and the prevention of complications, screening, diagnosis and treatment of women's cancers (particularly ovarian, cervical, endometrial and breast), pregnancy, birth and the care of new borns.  Commitment also extends to quality of life issues for women, including infertility, period problems, the menopause, endometriosis, incontinence and osteoporosis.  Provides information leaflets on all aspects of women's health and pregnancy.  Self or any referral.</entry>
</Desc>
<Pubs><entry>Newsletter; Health Information; Annual Report; Leaflets</entry>
</Pubs>
<CharityNo><entry>239281</entry>
</CharityNo>
<Address><entry>37 Canterbury Avenue</entry>
<entry>Sheffield</entry>
<entry>South Yorkshire</entry>
<entry>S10 3RU</entry>
</Address>
<ContactName><entry>Mrs Maureen Leach, Honorary Secretary</entry>
</ContactName>
<Telephone><entry>0114 230 5073</entry>
</Telephone>
<category><entry>WOMENS HEALTH</entry>
</category>
</SheffieldHYS>
