<SheffieldHYS id="21709">
<BaseURL><entry>http://www.sheffieldhelpyourself.org.uk/full_search_new.asp?group=21709</entry>
</BaseURL>
<HYSID><entry>21709</entry>
</HYSID>
<OrgName><entry>YEMENI WELFARE AND ADVICE CENTRE</entry>
</OrgName>
<Desc><entry>Offers advice in the following areas: benefits, immigration, employment, housing, consumer, tax, debt, child support, relationship breakdown, etc.  Home visits.  Helps with reviews and represents at tribunals.  Participates in summer festival.  Self or any referral.</entry>
</Desc>
<Langs><entry>Arabic</entry>
</Langs>
<Pubs><entry>Leaflets</entry>
</Pubs>
<CharityNo><entry>1079330</entry>
</CharityNo>
<Address><entry>Firvale Centre</entry>
<entry>Old Earl Marshal School</entry>
<entry>Earl Marshal Road</entry>
<entry>Sheffield</entry>
<entry>South Yorkshire</entry>
<entry>S4 8LA</entry>
</Address>
<DisabledAccess><entry>Wheelchair Accessible;</entry>
<entry>Wheelchair Accessible Toilet;</entry>
<entry>Lift</entry>
</DisabledAccess>
<ContactName><entry>Nageeb Kheili</entry>
</ContactName>
<Telephone><entry>0114 303 0148</entry>
</Telephone>
<Email><entry>nkheili@ycasheffield.co.uk</entry>
</Email>
<ProviderServiceDetails><entry>Mon,Tues &amp; Thurs 9.30am-2pm (drop-in advice sessions), Wed (by appointment only)</entry>
</ProviderServiceDetails>
<Provision><ProvisionPlace><entry>Yemeni Community Centre</entry>
<entry>68 Burngreave Road</entry>
<entry>Sheffield</entry>
<entry>South Yorkshire</entry>
<entry>S3 9DD</entry>
</ProvisionPlace>
<ProvisionDaysAndTimes><entry>Please contact for details of drop-in sessions</entry>
</ProvisionDaysAndTimes>
</Provision>
<category><entry>ADVICE SERVICES</entry>
</category>
</SheffieldHYS>
