<SheffieldHYS id="23517">
<BaseURL><entry>http://www.sheffieldhelpyourself.org.uk/full_search_new.asp?group=23517</entry>
</BaseURL>
<HYSID><entry>23517</entry>
</HYSID>
<OrgName><entry>CAPOEIRA</entry>
</OrgName>
<Desc><entry>A Brazilian martial art which blends together music, dance and fighting skills.  Open to males and females, all ages and sections of the community.</entry>
</Desc>
<Website><entry>http://www.cdonotts.co.uk</entry>
</Website>
<Langs><entry>Italian, Portuguese</entry>
</Langs>
<Address><entry>Please contact for details</entry>
</Address>
<ContactName><entry>Mauro Tatanka</entry>
<entry>Mobile:</entry>
<entry>07898 992042</entry>
</ContactName>
<Provision><ProvisionPlace><entry>Victoria Hall</entry>
<entry>Norfolk Street</entry>
<entry>Sheffield</entry>
<entry>South Yorkshire</entry>
<entry>S1 2JB</entry>
</ProvisionPlace>
<ProvisionPlaceDisabledAccess><entry>Wheelchair Accessible;</entry>
<entry>Wheelchair Accessible Toilet;</entry>
</ProvisionPlaceDisabledAccess>
<ProvisionDaysAndTimes><entry>Mon &amp; Thurs 7-8.30pm</entry>
</ProvisionDaysAndTimes>
<Telephone><entry>0114 272 1749</entry>
</Telephone>
</Provision>
<category><entry>MARTIAL ARTS - TAI CHI, QI GONG AND CAPOEIRA</entry>
</category>
</SheffieldHYS>
