<SheffieldHYS id="24083">
<BaseURL><entry>http://www.sheffieldhelpyourself.org.uk/full_search_new.asp?group=24083</entry>
</BaseURL>
<HYSID><entry>24083</entry>
</HYSID>
<OrgName><entry>AL-RAHMAN MOSQUE</entry>
</OrgName>
<Desc><entry>Mainly, but not exclusively attended by people from the Yemeni community.</entry>
</Desc>
<Address><entry>3 Ellesmere Road</entry>
<entry>Sheffield</entry>
<entry>South Yorkshire</entry>
<entry>S4 7JA</entry>
</Address>
<postcode><entry>Mobile:</entry>
<entry>07533 439121, Mosque</entry>
</postcode>
<category><entry>MOSQUES</entry>
</category>
</SheffieldHYS>
