<SheffieldHYS id="24637">
<BaseURL><entry>http://www.sheffieldhelpyourself.org.uk/full_search_new.asp?group=24637</entry>
</BaseURL>
<HYSID><entry>24637</entry>
</HYSID>
<OrgName><entry>SOUTH YORKSHIRE HEALERS AND YORKSHIRE MEDIUMS</entry>
</OrgName>
<Desc><entry>Endeavours to raise the standards of healers, mediums and psychics by providing training and insurance.  Holds regular meetings, healing exchanges and workshop days.  Also runs Sheffield Paranormal Investigations (SPI), see separate entry.</entry>
</Desc>
<Website><entry>http://www.southyorkshirehealers.co.uk</entry>
</Website>
<Address><entry>Please contact for details</entry>
</Address>
<ContactName><entry>Brenda Diskin</entry>
</ContactName>
<Telephone><entry>0114 221 5207</entry>
</Telephone>
<Email><entry>sacredearth2@hotmail.com</entry>
</Email>
<category><entry>CLAIRVOYANTS, TAROT CARD READERS AND MEDIUMS</entry>
</category>
</SheffieldHYS>
