<SheffieldHYS id="24998">
<BaseURL><entry>http://www.sheffieldhelpyourself.org.uk/full_search_new.asp?group=24998</entry>
</BaseURL>
<HYSID><entry>24998</entry>
</HYSID>
<OrgName><entry>BUSY BEES CRAFTS</entry>
</OrgName>
<Desc><entry>Friendly craft workshops with the staff of Busy Bee's Crafts. Please contact or see website for further details.</entry>
</Desc>
<Website><entry>http://www.busybeescrafts.org.uk</entry>
</Website>
<Address><entry>18 Cross Street</entry>
<entry>Sheffield</entry>
<entry>South Yorkshire</entry>
<entry>S13 7JR</entry>
</Address>
<Telephone><entry>0114 254 0234</entry>
</Telephone>
<Email><entry>info@busybeescrafts.org.uk</entry>
</Email>
<ProviderServiceDetails><entry>Wed 2-4pm</entry>
</ProviderServiceDetails>
<category><entry>CRAFT SOCIETIES</entry>
</category>
</SheffieldHYS>
