<SheffieldHYS id="25132">
<BaseURL><entry>http://www.sheffieldhelpyourself.org.uk/full_search_new.asp?group=25132</entry>
</BaseURL>
<HYSID><entry>25132</entry>
</HYSID>
<OrgName><entry>BROOMHALL WOMENS HEALTH GROUP</entry>
</OrgName>
<Desc><entry>Open to women living in Broomhall.  Meets for holistic health activities such as chairobics, exercise class, healthy eating and complementary therapy.</entry>
</Desc>
<Address><entry>722 Prince of Wales Road</entry>
<entry>Sheffield</entry>
<entry>South Yorkshire</entry>
<entry>S9 4EU</entry>
</Address>
<DisabledAccess><entry>Wheelchair Accessible with Assistance;</entry>
<entry>Wheelchair Accessible Toilet;</entry>
</DisabledAccess>
<ContactName><entry>Fatima Musa</entry>
<entry>Mobile:</entry>
<entry>07967 724095</entry>
</ContactName>
<Provision><ProvisionPlace><entry>Broomhall Centre</entry>
<entry>Broomspring Lane</entry>
<entry>Sheffield</entry>
<entry>South Yorkshire</entry>
<entry>S10 2FD</entry>
</ProvisionPlace>
<ProvisionPlaceDisabledAccess><entry>Wheelchair Accessible;</entry>
<entry>Wheelchair Accessible Toilet;</entry>
</ProvisionPlaceDisabledAccess>
<ProvisionDaysAndTimes><entry>Thurs 10am-12.30pm</entry>
</ProvisionDaysAndTimes>
</Provision>
<category><entry>WOMENS HEALTH</entry>
</category>
</SheffieldHYS>
