<SheffieldHYS id="16623">
<BaseURL><entry>http://www.sheffieldhelpyourself.org.uk/full_search_new.asp?group=16623</entry>
</BaseURL>
<HYSID><entry>16623</entry>
</HYSID>
<OrgName><entry>ASSOCIATION OF SHEFFIELD THERAPISTS</entry>
</OrgName>
<Desc><entry>Qualified therapists accredited members of BACP, members of BASRT.  Provide individual/couple, children and group counselling, and psychosexual counselling to individuals and couples with sexual dysfunction problems.  Costs approx £45 for individuals, and approx £50 for couples.  Please contact for up-to-date details of prices.</entry>
</Desc>
<Address><entry>148 Baslow Road</entry>
<entry>Sheffield</entry>
<entry>South Yorkshire</entry>
<entry>S17 4DR</entry>
</Address>
<ContactName><entry>June Boorman/Kate Willcox</entry>
</ContactName>
<Telephone><entry>0114 234 0452</entry>
<entry>Telephone 1 Details:</entry>
<entry>June Boorman</entry>
<entry>0114 249 1280</entry>
<entry>Telephone 2 Details:</entry>
<entry>Kate Willcox</entry>
</Telephone>
<Fax><entry>0114 234 0452 (June Boorman)</entry>
<entry>Mobile:</entry>
<entry>07971 000693, June Boorman</entry>
<entry>Mobile:</entry>
<entry>07794 899467, Kate Willcox</entry>
</Fax>
<Email><entry>juneboorman@blueyonder.co.uk</entry>
<entry>katewillcox@hotmail.co.uk</entry>
</Email>
<Provision><ProvisionPlace><entry>148 Baslow Road</entry>
<entry>Sheffield</entry>
<entry>South Yorkshire</entry>
<entry>S17 4DR</entry>
</ProvisionPlace>
<ProvisionDaysAndTimes><entry>Usually day and evenings, please contact for an appointment</entry>
</ProvisionDaysAndTimes>
</Provision>
<category><entry>COUNSELLING AND THERAPY - PRIVATE SERVICES</entry>
</category>
</SheffieldHYS>
