<SheffieldHYS id="17630">
<BaseURL><entry>http://www.sheffieldhelpyourself.org.uk/full_search_new.asp?group=17630</entry>
</BaseURL>
<HYSID><entry>17630</entry>
</HYSID>
<OrgName><entry>DON VALLEY STADIUM - FITNESS SUITE</entry>
</OrgName>
<Desc><entry>An induction course is necessary before the facilities can be used.  Facilities available free to members includes; fitness testing, health profile, programme run through and motivation techniques. Users must be aged 16 years or over.  Children aged 11-15 years must be accompanied by a parent/guardian.  Is an IFI accredited facility.  Accepts slice cards.</entry>
</Desc>
<Website><entry>http://www.donvalley-stadium.co.uk</entry>
</Website>
<Pubs><entry>Newsletter</entry>
</Pubs>
<Address><entry>Worksop Road</entry>
<entry>Sheffield</entry>
<entry>South Yorkshire</entry>
<entry>S9 3TL</entry>
</Address>
<DisabledAccess><entry>Wheelchair Accessible;</entry>
<entry>Wheelchair Accessible Toilet;</entry>
<entry>Lift, Unisex Accessible Changing Room</entry>
</DisabledAccess>
<ContactName><entry>Christine Green, Quality and Customer Service Manager/Yan Maychrzak</entry>
</ContactName>
<Telephone><entry>0114 223 3617</entry>
<entry>Telephone 1 Details:</entry>
<entry>Fitness Suite</entry>
<entry>0114 223 3638</entry>
</Telephone>
<Fax><entry>0114 243 4270</entry>
</Fax>
<Email><entry>info@donvalley-stadium.co.uk</entry>
<entry>j.maychrzak@sivltd.com</entry>
</Email>
<ProviderServiceDetails><entry>Mon-Fri 9am-5pm (office times), Mon-Thurs 7am-9pm, Fri 7am-8.30pm, Sat &amp; Sun 9am-5pm (fitness suite).</entry>
</ProviderServiceDetails>
<category><entry>WEIGHT TRAINING AND FITNESS CENTRES</entry>
</category>
</SheffieldHYS>
