<SheffieldHYS id="19646">
<BaseURL><entry>http://www.sheffieldhelpyourself.org.uk/full_search_new.asp?group=19646</entry>
</BaseURL>
<HYSID><entry>19646</entry>
</HYSID>
<OrgName><entry>PUBLIC RIGHTS OF WAY GROUP</entry>
</OrgName>
<Desc><entry>Produces the definitive map of public rights of way (public footpaths, bridleways and byways) for the area.  Operates a general enquiries service for public rights of way and investigates complaints about obstructed paths etc (by appointment only).  Maintains and signposts public paths.  Deals with claimed paths and with the new Countryside and Rights of Way Act requirements.  Encourages the use and enjoyment of public paths and the reporting back of any problems encountered.  Runs the Adopt-a-Path scheme where members walk a specified route or network of paths in an area of their choice to ensure that they are in satisfactory condition and send in report forms.  Organises talks and lectures on rights of way legislation, maintenance problems and offers general advice on rights of way matters.</entry>
</Desc>
<Website><entry>http://www.sheffield.gov.uk</entry>
</Website>
<Address><entry>Public Rights of Way Group</entry>
<entry>Transport and Highways</entry>
<entry>Howden House</entry>
<entry>1 Union Street</entry>
<entry>Sheffield</entry>
<entry>South Yorkshire</entry>
<entry>S1 2SH</entry>
</Address>
<DisabledAccess><entry>Wheelchair Accessible;</entry>
<entry>Wheelchair Accessible Toilet;</entry>
<entry>Lift</entry>
</DisabledAccess>
<ContactName><entry>Mick Hanson, Principal Public Rights of Way Officer</entry>
</ContactName>
<Telephone><entry>0114 273 4448</entry>
<entry>0114 273 6117</entry>
</Telephone>
<Fax><entry>0114 273 6358</entry>
</Fax>
<Email><entry>publicrightsofway@sheffield.gov.uk</entry>
</Email>
<ProviderServiceDetails><entry>Mon-Fri 9am-5pm</entry>
</ProviderServiceDetails>
<category><entry>ENVIRONMENT AND CONSERVATION</entry>
</category>
</SheffieldHYS>
