<SheffieldHYS id="19910">
<BaseURL><entry>http://www.sheffieldhelpyourself.org.uk/full_search_new.asp?group=19910</entry>
</BaseURL>
<HYSID><entry>19910</entry>
</HYSID>
<OrgName><entry>SHARE PSYCHOTHERAPY</entry>
</OrgName>
<AltName><entry>CONTACT GROUP TRUST (FORMER NAME)</entry>
</AltName>
<Desc><entry>A registered charity which offers long-term psychoanalytic psychotherapy for individuals (aged 14 years and over) who have a variety of problems, including difficulties with relationships, depression and anxiety.  Also offers couple, family and group therapy.  Information pack includes an application form.  Assessment appointment normally offered within 2 weeks of the application form being received.  Costs for therapy sessions depend on individual annual incomes.  Company limited by guarantee no 06757789.  Self or any referral.</entry>
</Desc>
<Website><entry>http://www.sharepsychotherapy.org</entry>
</Website>
<Langs><entry>French, Serbo-Croat</entry>
</Langs>
<Pubs><entry>Annual Report; Information booklet and application pack</entry>
</Pubs>
<CharityNo><entry>1130400</entry>
</CharityNo>
<Address><entry>73 Wilkinson Street</entry>
<entry>Sheffield</entry>
<entry>South Yorkshire</entry>
<entry>S10 2GJ</entry>
</Address>
<ContactName><entry>Pam Johnson, Office Manager</entry>
</ContactName>
<Telephone><entry>0114 273 0200</entry>
<entry>Telephone 1 Details:</entry>
<entry>Mon-Thurs 10.30am-3.30pm, and answerphone</entry>
</Telephone>
<Email><entry>office@sharepsychotherapy.org</entry>
</Email>
<ProviderServiceDetails><entry>No public callers without a prior appointment</entry>
</ProviderServiceDetails>
<category><entry>COUNSELLING AND THERAPY - CHARITABLE AND VOLUNTARY SERVICES</entry>
</category>
</SheffieldHYS>
