<SheffieldHYS id="20251">
<BaseURL><entry>http://www.sheffieldhelpyourself.org.uk/full_search_new.asp?group=20251</entry>
</BaseURL>
<HYSID><entry>20251</entry>
</HYSID>
<OrgName><entry>SHEFFIELD HALLAM UNIVERSITY CONFERENCE 21 - VENUES FOR HIRE</entry>
</OrgName>
<AltName><entry>SHU CITY CAMPUS [FORMER NAME]</entry>
</AltName>
<Desc><entry>Various lecture theatres/rooms available for hire from maximum capacity 450 to smaller meeting rooms capacity 10 upwards.  Private dining for up to 100 people.  Available weekends and evenings, especially during vacation times.</entry>
</Desc>
<Website><entry>http://www.shu.ac.uk/conference21</entry>
</Website>
<Address><entry>Sheffield Hallam University</entry>
<entry>City Campus</entry>
<entry>Howard Street</entry>
<entry>Sheffield</entry>
<entry>South Yorkshire</entry>
<entry>S1 1WB</entry>
</Address>
<DisabledAccess><entry>Wheelchair Accessible;</entry>
<entry>Wheelchair Accessible Toilet;</entry>
</DisabledAccess>
<ContactName><entry>Becky Stanyard/Jill Hitchenor</entry>
</ContactName>
<Telephone><entry>0114 225 5336</entry>
<entry>Telephone 1 Details:</entry>
<entry>Mon-Fri 8.45am-5.15pm</entry>
<entry>0114 225 5319</entry>
</Telephone>
<Fax><entry>0114 225 5337</entry>
</Fax>
<Email><entry>conference21@shu.ac.uk</entry>
</Email>
<category><entry>VENUES FOR HIRE - CITYWIDE</entry>
</category>
</SheffieldHYS>
