<SheffieldHYS id="20925">
<BaseURL><entry>http://www.sheffieldhelpyourself.org.uk/full_search_new.asp?group=20925</entry>
</BaseURL>
<HYSID><entry>20925</entry>
</HYSID>
<OrgName><entry>CHURCH OF ST FRANCIS OF ASSISI</entry>
</OrgName>
<Desc><entry>Roman Catholic church covering the parish area between Fulwood Road, Manchester Road and up to Lodge Moor.</entry>
</Desc>
<Pubs><entry>Newsletter; Parish Directory</entry>
</Pubs>
<CharityNo><entry>512021</entry>
</CharityNo>
<Address><entry>Presbytery</entry>
<entry>277 Sandygate Road</entry>
<entry>Sheffield</entry>
<entry>South Yorkshire</entry>
<entry>S10 5SD</entry>
</Address>
<ContactName><entry>The Parish Priest</entry>
</ContactName>
<Telephone><entry>0114 263 0383</entry>
</Telephone>
<Provision><ProvisionPlace><entry>Church of St Francis of Assisi</entry>
<entry>Sandygate Road</entry>
<entry>Sheffield</entry>
<entry>South Yorkshire</entry>
<entry>S10 5SD</entry>
</ProvisionPlace>
<ProvisionPlaceDisabledAccess><entry>Wheelchair Accessible;</entry>
<entry>Wheelchair Accessible Toilet;</entry>
</ProvisionPlaceDisabledAccess>
<ProvisionDaysAndTimes><entry>Sunday Mass at 9am &amp; 11am</entry>
</ProvisionDaysAndTimes>
</Provision>
<category><entry>ROMAN CATHOLIC CHURCHES</entry>
</category>
</SheffieldHYS>
