<SheffieldHYS id="22300">
<BaseURL><entry>http://www.sheffieldhelpyourself.org.uk/full_search_new.asp?group=22300</entry>
</BaseURL>
<HYSID><entry>22300</entry>
</HYSID>
<OrgName><entry>AIESEC SHEFFIELD</entry>
</OrgName>
<Desc><entry>A registered charity which is a branch of a global non-profit organisation.  Runs an exchange programme placing students in a variety of international internships as a means of combating a variety of issues.  Works to bring qualified and motivated international students to the UK and place them in a business in the South Yorkshire region.  Is a member of the Junior Chamber of Commerce and has close links with several other networking organisations.  Develops its members to be the socially responsible leaders of tomorrow.  Self or any referral.</entry>
</Desc>
<Website><entry>http://www.aiesec.co.uk</entry>
</Website>
<CharityNo><entry>274779</entry>
</CharityNo>
<Address><entry>The University of Sheffield Union of Students</entry>
<entry>Western Bank</entry>
<entry>Sheffield</entry>
<entry>South Yorkshire</entry>
<entry>S10 2TG</entry>
</Address>
<DisabledAccess><entry>Wheelchair Accessible;</entry>
<entry>Wheelchair Accessible Toilet;</entry>
</DisabledAccess>
<ContactName><entry>Kush Ahuja, President</entry>
<entry>Mobile:</entry>
<entry>07772 910341</entry>
</ContactName>
<Email><entry>kush.me.ahuja@gmail.com</entry>
</Email>
<ProviderServiceDetails><entry>Please contact for an appointment</entry>
</ProviderServiceDetails>
<category><entry>SPECIALIST VOCATIONAL TRAINING</entry>
</category>
</SheffieldHYS>
