<SheffieldHYS id="22923">
<BaseURL><entry>http://www.sheffieldhelpyourself.org.uk/full_search_new.asp?group=22923</entry>
</BaseURL>
<HYSID><entry>22923</entry>
</HYSID>
<OrgName><entry>ST DUNSTANS TRAINING CENTRE SHEFFIELD</entry>
</OrgName>
<Desc><entry>A registered charity that seeks to help blind or partially sighted ex-service men and women regain their confidence and self esteem to live independent and satisfying lives.  Offers training in computer skills and learning independent living skills.  Company limited by guarantee no 189648.</entry>
</Desc>
<Website><entry>http://www.st-dunstans.org.uk</entry>
</Website>
<CharityNo><entry>216227</entry>
</CharityNo>
<Address><entry>276 Fulwood Road</entry>
<entry>Sheffield</entry>
<entry>South Yorkshire</entry>
<entry>S10 3BN</entry>
</Address>
<DisabledAccess><entry>Wheelchair Accessible;</entry>
<entry>Wheelchair Accessible Toilet;</entry>
</DisabledAccess>
<ContactName><entry>Terry Heaton, Centre Manager</entry>
</ContactName>
<Telephone><entry>0114 267 2550</entry>
<entry>Telephone 1 Details:</entry>
<entry>and answerphone</entry>
<entry>0114 267 2580</entry>
<entry>Telephone 2 Details:</entry>
<entry>and answerphone</entry>
</Telephone>
<Fax><entry>0114 267 2591</entry>
</Fax>
<Email><entry>enquiries@st-dunstans.org.uk</entry>
</Email>
<ProviderServiceDetails><entry>Mon-Fri 9am-5pm</entry>
</ProviderServiceDetails>
<category><entry>BLINDNESS AND VISUAL IMPAIRMENT</entry>
</category>
</SheffieldHYS>
