<SheffieldHYS id="24941">
<BaseURL><entry>http://www.sheffieldhelpyourself.org.uk/full_search_new.asp?group=24941</entry>
</BaseURL>
<HYSID><entry>24941</entry>
</HYSID>
<OrgName><entry>YOGA FOR HEALTH</entry>
</OrgName>
<Desc><entry>Comprehensive yoga covering postures, breathing and gentle stretches, by a qualified yoga instructor, for adults.  Please bring a mat.  Beginners welcome.  Friendly yoga with a smile.</entry>
</Desc>
<Address><entry>Please contact for details</entry>
</Address>
<ContactName><entry>Ann Zielonka</entry>
</ContactName>
<Telephone><entry>0114 236 1585</entry>
<entry>Mobile:</entry>
<entry>07929 736966</entry>
</Telephone>
<Provision><ProvisionPlace><entry>Millennium Hall</entry>
<entry>518-520 Ecclesall Road</entry>
<entry>Sheffield</entry>
<entry>South Yorkshire</entry>
<entry>S11 8PY</entry>
</ProvisionPlace>
<ProvisionPlaceDisabledAccess><entry>Wheelchair Accessible;</entry>
<entry>Further Access Details:</entry>
<entry>Via Wilson Road entrance</entry>
</ProvisionPlaceDisabledAccess>
<ProvisionDaysAndTimes><entry>Tues 8-9.30pm</entry>
</ProvisionDaysAndTimes>
<ProvisionPlace><entry>Broomhill Methodist Church</entry>
<entry>Fulwood Road</entry>
<entry>Sheffield</entry>
<entry>South Yorkshire</entry>
<entry>S10 3BD</entry>
</ProvisionPlace>
<ProvisionPlaceDisabledAccess><entry>Wheelchair Accessible;</entry>
<entry>Wheelchair Accessible Toilet;</entry>
</ProvisionPlaceDisabledAccess>
<ProvisionDaysAndTimes><entry>Thurs 6-7.30pm, 7.45-9.15pm</entry>
</ProvisionDaysAndTimes>
</Provision>
<category><entry>YOGA AND PILATES</entry>
</category>
</SheffieldHYS>
