<SheffieldHYS id="25123">
<BaseURL><entry>http://www.sheffieldhelpyourself.org.uk/full_search_new.asp?group=25123</entry>
</BaseURL>
<HYSID><entry>25123</entry>
</HYSID>
<OrgName><entry>DWARF SPORTS ASSOCIATION UK</entry>
</OrgName>
<Desc><entry>Aims to make regular sports and activities accessible and enjoyable to anyone and everyone of restricted growth in the UK.  Offers athletics, badminton, boccia, swimming as well as table tennis, cycling, new age curling, power lifting, football and basketball.  Contact can be made via the website.</entry>
</Desc>
<Website><entry>http://www.dsauk.org</entry>
</Website>
<Pubs><entry>Newsletter; Leaflets</entry>
</Pubs>
<CharityNo><entry>1041961</entry>
</CharityNo>
<Address><entry>PO Box 4269</entry>
<entry>Dronfield</entry>
<entry>North East Derbyshire</entry>
<entry>S18 9BG</entry>
</Address>
<ContactName><entry>Tim Shepherd</entry>
<entry>Mobile:</entry>
<entry>07889 922736</entry>
</ContactName>
<Provision><ProvisionPlace><entry>English Institute of Sport</entry>
<entry>Coleridge Road</entry>
<entry>Sheffield</entry>
<entry>South Yorkshire</entry>
<entry>S9 5DA</entry>
</ProvisionPlace>
<ProvisionPlaceDisabledAccess><entry>Wheelchair Accessible;</entry>
<entry>Wheelchair Accessible Toilet;</entry>
<entry>Further Access Details:</entry>
<entry>Lift to viewing and spectator areas</entry>
</ProvisionPlaceDisabledAccess>
<ProvisionDaysAndTimes><entry>Various times, please contact for details</entry>
</ProvisionDaysAndTimes>
<ProvisionPlace><entry>Don Valley Stadium</entry>
<entry>Worksop Road</entry>
<entry>Sheffield</entry>
<entry>South Yorkshire</entry>
<entry>S9 3TL</entry>
</ProvisionPlace>
<ProvisionPlaceDisabledAccess><entry>Wheelchair Accessible;</entry>
<entry>Wheelchair Accessible Toilet;</entry>
<entry>Further Access Details:</entry>
<entry>Lift</entry>
</ProvisionPlaceDisabledAccess>
<ProvisionDaysAndTimes><entry>Various times, please contact for details</entry>
</ProvisionDaysAndTimes>
</Provision>
<category><entry>DISABLED PEOPLE - GENERAL SUPPORT</entry>
</category>
</SheffieldHYS>
